hd_gliomouse/__init__.py
hd_gliomouse/hd_gliomouse_predict.py
hd_gliomouse/hd_gliomouse_predict_folder.py
hd_gliomouse/paths.py
hd_gliomouse/setup_hd_gliomouse.py
hd_gliomouse/utils.py
hd_gliomouse-1.1.dist-info/LICENSE
hd_gliomouse-1.1.dist-info/METADATA
hd_gliomouse-1.1.dist-info/WHEEL
hd_gliomouse-1.1.dist-info/entry_points.txt
hd_gliomouse-1.1.dist-info/top_level.txt
hd_gliomouse-1.1.dist-info/RECORD
